climax/__init__.py
climax/_imagepanel.py
climax/_renderer.py
climax/_slider.py
climax/climax.py
climax/climax.tcss
climax/climax_logo_100x100.png
climax/climax_rs.cp314t-win32.pyd
climax/profile.py
climax/version.py
climax_rfglab-2025.10.1.dist-info/METADATA
climax_rfglab-2025.10.1.dist-info/WHEEL
climax_rfglab-2025.10.1.dist-info/entry_points.txt
climax_rfglab-2025.10.1.dist-info/licenses/LICENSE
climax_rfglab-2025.10.1.dist-info/RECORD
