Metadata-Version: 2.4
Name: climax-rfglab
Version: 2025.10.1
Classifier: Programming Language :: Python :: 3.10
Classifier: Programming Language :: Python :: 3.11
Classifier: Programming Language :: Python :: 3.12
Classifier: Programming Language :: Python :: 3.13
Classifier: Operating System :: OS Independent
Requires-Dist: numpy==2.2.1
Requires-Dist: matplotlib==3.10.0
Requires-Dist: rich==14.1.0
Requires-Dist: rich-pixels==3.0.1
Requires-Dist: scikit-image==0.25.0
Requires-Dist: textual==1.0.0
Requires-Dist: textual-fspicker==0.4.1
Requires-Dist: textual-plotext==1.0.1
Requires-Dist: tifffile==2025.9.9
License-File: LICENSE
Summary: climax is a Command Line IMAge eXplorer
Author-email: Rodrigo Fernandez-Gonzalez <rodrigo.fernandez.gonzalez@utoronto.ca>
License-Expression: GPL-3.0-or-later
Requires-Python: >=3.10
Project-URL: Homepage, https://bitbucket.com/rfg_lab/climax
Project-URL: Bug Tracker, https://bitbucket.com/rfg_lab/climax/issues
